{
    "name": "Uniswap Default List",
    "timestamp": "2021-01-21T23:57:10.982Z",
    "version": {
        "major": 2,
        "minor": 0,
        "patch": 0
    },
    "tags": {},
    "logoURI": "ipfs://QmNa8mQkrNKp1WEEeGjFezDmDeodkWRevGFN8JCV7b4Xir",
    "keywords": [
        "uniswap",
        "default"
    ],
    "tokens": [
        {
            "name": "PIGUSDT",
            "address": "0xC5b47475fc4F81323F0945753C2b03B97e7161DC",
            "symbol": "MOCKUSDT",
            "decimals": 18,
            "chainId": 128,
            "logoURI": "https://ss0.bdstatic.com/70cFvHSh_Q1YnxGkpoWK1HF6hhy/it/u=1021744422,3395550928&fm=26&gp=0.jpg"
        },
        {
            "name": "PIGUSDT",
            "address": "0xfAeC8fF710A33485b2476df38a465c58Aa89326F",
            "symbol": "PIGUSDT",
            "decimals": 18,
            "chainId": 128,
            "logoURI": "https://ss0.bdstatic.com/70cFvHSh_Q1YnxGkpoWK1HF6hhy/it/u=1021744422,3395550928&fm=26&gp=0.jpg"
        },
        {
            "name": "PIGDAI",
            "address": "0x0053e191F55b1757a0c1F527bD250614f774E867",
            "symbol": "PIGDAI",
            "decimals": 18,
            "chainId": 128,
            "logoURI": "https://ss0.bdstatic.com/70cFvHSh_Q1YnxGkpoWK1HF6hhy/it/u=1021744422,3395550928&fm=26&gp=0.jpg"
        },
        {
            "name": "CAKE",
            "address": "0x95Ac069F3aF1cf37F3a9222d044b444745d7d947",
            "symbol": "CAKE",
            "decimals": 18,
            "chainId": 128,
            "logoURI": "https://ss0.bdstatic.com/70cFvHSh_Q1YnxGkpoWK1HF6hhy/it/u=1021744422,3395550928&fm=26&gp=0.jpg"
        },
        {
            "name": "PIGTEST",
            "address": "0x2E6E5F91ba26ad09e874Eb62a95b075eEFc7551F",
            "symbol": "PIGTEST",
            "decimals": 18,
            "chainId": 128,
            "logoURI": "https://ss0.bdstatic.com/70cFvHSh_Q1YnxGkpoWK1HF6hhy/it/u=1021744422,3395550928&fm=26&gp=0.jpg"
        },
        {
            "name": "LPT1",
            "address": "0xB8610C6379bF54C257A94615f8Fd7edC84ae52E3",
            "symbol": "LPT1",
            "decimals": 18,
            "chainId": 128,
            "logoURI": "https://ss0.bdstatic.com/70cFvHSh_Q1YnxGkpoWK1HF6hhy/it/u=1021744422,3395550928&fm=26&gp=0.jpg"
        },
        {
            "name": "LPT2",
            "address": "0x61B8BE0CD2e01f1b9CE361E20CA45315c9441D8E",
            "symbol": "LPT2",
            "decimals": 18,
            "chainId": 128,
            "logoURI": "https://ss0.bdstatic.com/70cFvHSh_Q1YnxGkpoWK1HF6hhy/it/u=1021744422,3395550928&fm=26&gp=0.jpg"
        },
        {
            "name": "LPT4",
            "address": "0xa32Ab4AFc1a129d39085892Aa85468F7ba77A5ee",
            "symbol": "LPT4",
            "decimals": 18,
            "chainId": 128,
            "logoURI": "https://ss0.bdstatic.com/70cFvHSh_Q1YnxGkpoWK1HF6hhy/it/u=1021744422,3395550928&fm=26&gp=0.jpg"
        },
        {
            "name": "PTT1",
            "address": "0xEDD284CC4550b1aBeaD2C569041d89aa6594a381",
            "symbol": "PTT1",
            "decimals": 18,
            "chainId": 128,
            "logoURI": "https://ss0.bdstatic.com/70cFvHSh_Q1YnxGkpoWK1HF6hhy/it/u=1021744422,3395550928&fm=26&gp=0.jpg"
        },
        {
            "name": "PTT2",
            "address": "0x69CdE1ED25774d4AF2e939f3c4569F3AD58069C0",
            "symbol": "PTT2",
            "decimals": 18,
            "chainId": 128,
            "logoURI": "https://ss0.bdstatic.com/70cFvHSh_Q1YnxGkpoWK1HF6hhy/it/u=1021744422,3395550928&fm=26&gp=0.jpg"
        },
        {
            "name": "PTT3",
            "address": "0xDBCa382Acc93D5da951D93fbba33a16921E4E1D9",
            "symbol": "PTT3",
            "decimals": 18,
            "chainId": 128,
            "logoURI": "https://ss0.bdstatic.com/70cFvHSh_Q1YnxGkpoWK1HF6hhy/it/u=1021744422,3395550928&fm=26&gp=0.jpg"
        },
        {
            "name": "PTT4",
            "address": "0x80b7300540b5f0a00016100cCD18396067B5477e",
            "symbol": "PTT4",
            "decimals": 18,
            "chainId": 128,
            "logoURI": "https://ss0.bdstatic.com/70cFvHSh_Q1YnxGkpoWK1HF6hhy/it/u=1021744422,3395550928&fm=26&gp=0.jpg"
        },
        {
            "name": "PTT5",
            "address": "0xBFff12cA187f283bD83d728fe2c1F3A5C7C8aa92",
            "symbol": "PTT5",
            "decimals": 18,
            "chainId": 128,
            "logoURI": "https://ss0.bdstatic.com/70cFvHSh_Q1YnxGkpoWK1HF6hhy/it/u=1021744422,3395550928&fm=26&gp=0.jpg"
        },
        {
            "name": "PIGJDZR",
            "symbol": "PIGJDZR",
            "chainId": 128,
            "decimals": 16,
            "logoURI": "https://ss0.bdstatic.com/70cFvHSh_Q1YnxGkpoWK1HF6hhy/it/u=1021744422,3395550928&fm=26&gp=0.jpg",
            "address": "0x0f1507E01f17Dd4DAbDA6b5ed2B5148f47919799"
        },
        {
            "name": "PIGFADL",
            "symbol": "PIGFADL",
            "chainId": 128,
            "decimals": 14,
            "logoURI": "https://ss0.bdstatic.com/70cFvHSh_Q1YnxGkpoWK1HF6hhy/it/u=1021744422,3395550928&fm=26&gp=0.jpg",
            "address": "0x6870853C591Dff0d622E9172583541d290db57De"
        },
        {
            "name": "PIGYIYA",
            "symbol": "PIGYIYA",
            "chainId": 128,
            "decimals": 12,
            "logoURI": "https://ss0.bdstatic.com/70cFvHSh_Q1YnxGkpoWK1HF6hhy/it/u=1021744422,3395550928&fm=26&gp=0.jpg",
            "address": "0xC45867F30886175f04598F336266e47147b92318"
        },
        {
            "name": "PIGUYBF",
            "symbol": "PIGUYBF",
            "chainId": 128,
            "decimals": 10,
            "logoURI": "https://ss0.bdstatic.com/70cFvHSh_Q1YnxGkpoWK1HF6hhy/it/u=1021744422,3395550928&fm=26&gp=0.jpg",
            "address": "0x67b355Ac8BcFf4F1bF0dd126275C804bb519A115"
        },
        {
            "name": "PIGMBUF",
            "symbol": "PIGMBUF",
            "chainId": 128,
            "decimals": 8,
            "logoURI": "https://ss0.bdstatic.com/70cFvHSh_Q1YnxGkpoWK1HF6hhy/it/u=1021744422,3395550928&fm=26&gp=0.jpg",
            "address": "0xD1F4a12cf552B11E3ccA7C681Dd7796eCa0DAB6e"
        },
        {
            "name": "PIGLDKB",
            "symbol": "PIGLDKB",
            "chainId": 128,
            "decimals": 18,
            "logoURI": "https://ss0.bdstatic.com/70cFvHSh_Q1YnxGkpoWK1HF6hhy/it/u=1021744422,3395550928&fm=26&gp=0.jpg",
            "address": "0xf26FCc840Ff92fCd678Ab4D85ca573695D81E4cf"
        },
        {
            "name": "PIGUQLH",
            "symbol": "PIGUQLH",
            "chainId": 128,
            "decimals": 18,
            "logoURI": "https://ss0.bdstatic.com/70cFvHSh_Q1YnxGkpoWK1HF6hhy/it/u=1021744422,3395550928&fm=26&gp=0.jpg",
            "address": "0xc6CE8cd5C9981C602E91aFe6911989fFcC44d18C"
        },
        {
            "name": "PIGFFXL",
            "symbol": "PIGFFXL",
            "chainId": 128,
            "decimals": 18,
            "logoURI": "https://ss0.bdstatic.com/70cFvHSh_Q1YnxGkpoWK1HF6hhy/it/u=1021744422,3395550928&fm=26&gp=0.jpg",
            "address": "0xA7ba9c6D58d6966816D2AaeB957de9673b533aB5"
        },
        {
            "name": "PIGIPNW",
            "symbol": "PIGIPNW",
            "chainId": 128,
            "decimals": 18,
            "logoURI": "https://ss0.bdstatic.com/70cFvHSh_Q1YnxGkpoWK1HF6hhy/it/u=1021744422,3395550928&fm=26&gp=0.jpg",
            "address": "0x6CcED80946e4c8ba5c74AC11779de904f5f569C9"
        },
        {
            "name": "PIGTSIF",
            "symbol": "PIGTSIF",
            "chainId": 128,
            "decimals": 18,
            "logoURI": "https://ss0.bdstatic.com/70cFvHSh_Q1YnxGkpoWK1HF6hhy/it/u=1021744422,3395550928&fm=26&gp=0.jpg",
            "address": "0x412755B8274B54b18602584d9edBa0731A51764c"
        },
        {
            "name": "PIGVAVN",
            "symbol": "PIGVAVN",
            "chainId": 128,
            "decimals": 18,
            "logoURI": "https://ss0.bdstatic.com/70cFvHSh_Q1YnxGkpoWK1HF6hhy/it/u=1021744422,3395550928&fm=26&gp=0.jpg",
            "address": "0x62DE6d6887E6D27c4EbE22fa5B45e400823a5587"
        },
        {
            "name": "PIGRBWZ",
            "symbol": "PIGRBWZ",
            "chainId": 128,
            "decimals": 18,
            "logoURI": "https://ss0.bdstatic.com/70cFvHSh_Q1YnxGkpoWK1HF6hhy/it/u=1021744422,3395550928&fm=26&gp=0.jpg",
            "address": "0xc0D68d512ebE8d862A83c252bE40160A473c8ea6"
        },
        {
            "name": "PIGOXNQ",
            "symbol": "PIGOXNQ",
            "chainId": 128,
            "decimals": 18,
            "logoURI": "https://ss0.bdstatic.com/70cFvHSh_Q1YnxGkpoWK1HF6hhy/it/u=1021744422,3395550928&fm=26&gp=0.jpg",
            "address": "0x5517B20A6a7601ea607212293B1f98cB7733A4a9"
        },
        {
            "name": "PIGULNL",
            "symbol": "PIGULNL",
            "chainId": 128,
            "decimals": 18,
            "logoURI": "https://ss0.bdstatic.com/70cFvHSh_Q1YnxGkpoWK1HF6hhy/it/u=1021744422,3395550928&fm=26&gp=0.jpg",
            "address": "0xf83727B390Ae2A4930273Fce5c8750dABED4Bc42"
        },
        {
            "name": "PIGTDIL",
            "symbol": "PIGTDIL",
            "chainId": 128,
            "decimals": 18,
            "logoURI": "https://ss0.bdstatic.com/70cFvHSh_Q1YnxGkpoWK1HF6hhy/it/u=1021744422,3395550928&fm=26&gp=0.jpg",
            "address": "0x495E433B73039A2FCb74401b301cEDac91Ba4d67"
        },
        {
            "name": "PIGGFNF",
            "symbol": "PIGGFNF",
            "chainId": 128,
            "decimals": 18,
            "logoURI": "https://ss0.bdstatic.com/70cFvHSh_Q1YnxGkpoWK1HF6hhy/it/u=1021744422,3395550928&fm=26&gp=0.jpg",
            "address": "0x7EFE4Aa0d252873E2c3Fcce6d604fAF39094c4c7"
        },
        {
            "name": "PIGJLXS",
            "symbol": "PIGJLXS",
            "chainId": 128,
            "decimals": 18,
            "logoURI": "https://ss0.bdstatic.com/70cFvHSh_Q1YnxGkpoWK1HF6hhy/it/u=1021744422,3395550928&fm=26&gp=0.jpg",
            "address": "0x689ad289F1Bb1C5695B20f1c31b29B48309A07A0"
        },
        {
            "name": "PIGDYZK",
            "symbol": "PIGDYZK",
            "chainId": 128,
            "decimals": 18,
            "logoURI": "https://ss0.bdstatic.com/70cFvHSh_Q1YnxGkpoWK1HF6hhy/it/u=1021744422,3395550928&fm=26&gp=0.jpg",
            "address": "0x85cD68bA036171c0cb0441509BbC8efC6210e1a7"
        },
        {
            "name": "PIGDOXU",
            "symbol": "PIGDOXU",
            "chainId": 128,
            "decimals": 18,
            "logoURI": "https://ss0.bdstatic.com/70cFvHSh_Q1YnxGkpoWK1HF6hhy/it/u=1021744422,3395550928&fm=26&gp=0.jpg",
            "address": "0x2b26f58bd61486688e56A428FaB3B112b6e38790"
        },
        {
            "name": "PIGDGWL",
            "symbol": "PIGDGWL",
            "chainId": 128,
            "decimals": 18,
            "logoURI": "https://ss0.bdstatic.com/70cFvHSh_Q1YnxGkpoWK1HF6hhy/it/u=1021744422,3395550928&fm=26&gp=0.jpg",
            "address": "0x35da47B39C527147089C68508000fe9Dae0B6aFE"
        },
        {
            "name": "PIGVLDF",
            "symbol": "PIGVLDF",
            "chainId": 128,
            "decimals": 18,
            "logoURI": "https://ss0.bdstatic.com/70cFvHSh_Q1YnxGkpoWK1HF6hhy/it/u=1021744422,3395550928&fm=26&gp=0.jpg",
            "address": "0x11af405338adEB2305B60D14651ba08CfaCA68fD"
        },
        {
            "name": "PIGQPNE",
            "symbol": "PIGQPNE",
            "chainId": 128,
            "decimals": 18,
            "logoURI": "https://ss0.bdstatic.com/70cFvHSh_Q1YnxGkpoWK1HF6hhy/it/u=1021744422,3395550928&fm=26&gp=0.jpg",
            "address": "0xE02F80086A1D6ac7eFD68ACCb9eEef83b9Ce7063"
        },
        {
            "name": "PIGMIUN",
            "symbol": "PIGMIUN",
            "chainId": 128,
            "decimals": 18,
            "logoURI": "https://ss0.bdstatic.com/70cFvHSh_Q1YnxGkpoWK1HF6hhy/it/u=1021744422,3395550928&fm=26&gp=0.jpg",
            "address": "0x7d1c129d483147048EEf2227ecC4058A13947DE0"
        },
        {
            "name": "PIGQHBM",
            "symbol": "PIGQHBM",
            "chainId": 128,
            "decimals": 18,
            "logoURI": "https://ss0.bdstatic.com/70cFvHSh_Q1YnxGkpoWK1HF6hhy/it/u=1021744422,3395550928&fm=26&gp=0.jpg",
            "address": "0x380c38b75610F07409870EF97fEcE2D59432e1bA"
        },
        {
            "name": "PIGWERT",
            "symbol": "PIGWERT",
            "chainId": 128,
            "decimals": 18,
            "logoURI": "https://ss0.bdstatic.com/70cFvHSh_Q1YnxGkpoWK1HF6hhy/it/u=1021744422,3395550928&fm=26&gp=0.jpg",
            "address": "0x957E9cB0E03B31122074Ca3E72A10fB2781D7342"
        },
        {
            "name": "PIGKEFU",
            "symbol": "PIGKEFU",
            "chainId": 128,
            "decimals": 18,
            "logoURI": "https://ss0.bdstatic.com/70cFvHSh_Q1YnxGkpoWK1HF6hhy/it/u=1021744422,3395550928&fm=26&gp=0.jpg",
            "address": "0x82F8C93bA8cF1B7e119760585B717d507Ccfbd69"
        },
        {
            "name": "PIGSMGY",
            "symbol": "PIGSMGY",
            "chainId": 128,
            "decimals": 18,
            "logoURI": "https://ss0.bdstatic.com/70cFvHSh_Q1YnxGkpoWK1HF6hhy/it/u=1021744422,3395550928&fm=26&gp=0.jpg",
            "address": "0xdca13b5D44D5595253C52B78AA5f56Ab1D852c71"
        },
        {
            "name": "PIGAPNF",
            "symbol": "PIGAPNF",
            "chainId": 128,
            "decimals": 18,
            "logoURI": "https://ss0.bdstatic.com/70cFvHSh_Q1YnxGkpoWK1HF6hhy/it/u=1021744422,3395550928&fm=26&gp=0.jpg",
            "address": "0x2E843e4Bc6e0D480412A9Aaf3927b8Ef4B122b5E"
        },
        {
            "name": "PIGMTCA",
            "symbol": "PIGMTCA",
            "chainId": 128,
            "decimals": 18,
            "logoURI": "https://ss0.bdstatic.com/70cFvHSh_Q1YnxGkpoWK1HF6hhy/it/u=1021744422,3395550928&fm=26&gp=0.jpg",
            "address": "0xD5Bca4d14C64811739Deca22081E3B4c1305CdD6"
        },
        {
            "name": "PIGQAAO",
            "symbol": "PIGQAAO",
            "chainId": 128,
            "decimals": 18,
            "logoURI": "https://ss0.bdstatic.com/70cFvHSh_Q1YnxGkpoWK1HF6hhy/it/u=1021744422,3395550928&fm=26&gp=0.jpg",
            "address": "0xf2CB17c881fAfb179DA7CAe26b4D16Dc8e180FB5"
        },
        {
            "name": "PIGVZAP",
            "symbol": "PIGVZAP",
            "chainId": 128,
            "decimals": 18,
            "logoURI": "https://ss0.bdstatic.com/70cFvHSh_Q1YnxGkpoWK1HF6hhy/it/u=1021744422,3395550928&fm=26&gp=0.jpg",
            "address": "0x9Fe6d07Db7E17803C3C22E2A93fc866b6cF6ce59"
        },
        {
            "name": "PIGJSYT",
            "symbol": "PIGJSYT",
            "chainId": 128,
            "decimals": 18,
            "logoURI": "https://ss0.bdstatic.com/70cFvHSh_Q1YnxGkpoWK1HF6hhy/it/u=1021744422,3395550928&fm=26&gp=0.jpg",
            "address": "0x581419A2D2bC2391C29290822936B8Ef6F2da103"
        },
        {
            "name": "PIGZLAZ",
            "symbol": "PIGZLAZ",
            "chainId": 128,
            "decimals": 18,
            "logoURI": "https://ss0.bdstatic.com/70cFvHSh_Q1YnxGkpoWK1HF6hhy/it/u=1021744422,3395550928&fm=26&gp=0.jpg",
            "address": "0x6Bac0b1e3BA67989D96d2aa0F3b6C59FA07f7218"
        },
        {
            "name": "PIGFEPQ",
            "symbol": "PIGFEPQ",
            "chainId": 128,
            "decimals": 18,
            "logoURI": "https://ss0.bdstatic.com/70cFvHSh_Q1YnxGkpoWK1HF6hhy/it/u=1021744422,3395550928&fm=26&gp=0.jpg",
            "address": "0xC0b1F2261DCe85d43d24152B0afa650C38b7BB1A"
        },
        {
            "name": "PIGPJOV",
            "symbol": "PIGPJOV",
            "chainId": 128,
            "decimals": 18,
            "logoURI": "https://ss0.bdstatic.com/70cFvHSh_Q1YnxGkpoWK1HF6hhy/it/u=1021744422,3395550928&fm=26&gp=0.jpg",
            "address": "0xAeB6e24dA2C6E2Dc7Cc082e3666eB045DD444c1d"
        },
        {
            "name": "PIGKXYW",
            "symbol": "PIGKXYW",
            "chainId": 128,
            "decimals": 18,
            "logoURI": "https://ss0.bdstatic.com/70cFvHSh_Q1YnxGkpoWK1HF6hhy/it/u=1021744422,3395550928&fm=26&gp=0.jpg",
            "address": "0xC8ddD6E583f6672a9fD142fD506FBf5eC34AC8Cd"
        },
        {
            "name": "PIGXFZG",
            "symbol": "PIGXFZG",
            "chainId": 128,
            "decimals": 18,
            "logoURI": "https://ss0.bdstatic.com/70cFvHSh_Q1YnxGkpoWK1HF6hhy/it/u=1021744422,3395550928&fm=26&gp=0.jpg",
            "address": "0xA2D482D30201151c1A1Fa4aE8BBBd0Ad5fdbbed4"
        },
        {
            "name": "PIGFZED",
            "symbol": "PIGFZED",
            "chainId": 128,
            "decimals": 18,
            "logoURI": "https://ss0.bdstatic.com/70cFvHSh_Q1YnxGkpoWK1HF6hhy/it/u=1021744422,3395550928&fm=26&gp=0.jpg",
            "address": "0xBAFEa22Cd9Cc5E15fdFA73bC3c451a48595e9c9c"
        },
        {
            "name": "PIGOFGM",
            "symbol": "PIGOFGM",
            "chainId": 128,
            "decimals": 18,
            "logoURI": "https://ss0.bdstatic.com/70cFvHSh_Q1YnxGkpoWK1HF6hhy/it/u=1021744422,3395550928&fm=26&gp=0.jpg",
            "address": "0x94D7D8D282EfDab7d54638bD9a488AD4a7940Cbc"
        },
        {
            "name": "PIGOYOX",
            "symbol": "PIGOYOX",
            "chainId": 128,
            "decimals": 18,
            "logoURI": "https://ss0.bdstatic.com/70cFvHSh_Q1YnxGkpoWK1HF6hhy/it/u=1021744422,3395550928&fm=26&gp=0.jpg",
            "address": "0xAF3E59Aa4Ffb452649fA3Fe28033A3579EF33F45"
        },
        {
            "name": "PIGIJGI",
            "symbol": "PIGIJGI",
            "chainId": 128,
            "decimals": 18,
            "logoURI": "https://ss0.bdstatic.com/70cFvHSh_Q1YnxGkpoWK1HF6hhy/it/u=1021744422,3395550928&fm=26&gp=0.jpg",
            "address": "0x18680C55d5B51e56FEe0dB405B9820FfcAB324C3"
        },
        {
            "name": "PIGNTVE",
            "symbol": "PIGNTVE",
            "chainId": 128,
            "decimals": 18,
            "logoURI": "https://ss0.bdstatic.com/70cFvHSh_Q1YnxGkpoWK1HF6hhy/it/u=1021744422,3395550928&fm=26&gp=0.jpg",
            "address": "0xf7f40bb678B306dA7058adcDa0Fd97a1aba032b7"
        },
        {
            "name": "PIGYBMM",
            "symbol": "PIGYBMM",
            "chainId": 128,
            "decimals": 18,
            "logoURI": "https://ss0.bdstatic.com/70cFvHSh_Q1YnxGkpoWK1HF6hhy/it/u=1021744422,3395550928&fm=26&gp=0.jpg",
            "address": "0x87403429F6B878b4CC3f1b3B71e65c49CAc7D22C"
        },
        {
            "name": "PIGSYTF",
            "symbol": "PIGSYTF",
            "chainId": 128,
            "decimals": 18,
            "logoURI": "https://ss0.bdstatic.com/70cFvHSh_Q1YnxGkpoWK1HF6hhy/it/u=1021744422,3395550928&fm=26&gp=0.jpg",
            "address": "0x05CA833056E9f8646b9C8cF13FD1d190673Ff498"
        },
        {
            "name": "PIGSNMY",
            "symbol": "PIGSNMY",
            "chainId": 128,
            "decimals": 18,
            "logoURI": "https://ss0.bdstatic.com/70cFvHSh_Q1YnxGkpoWK1HF6hhy/it/u=1021744422,3395550928&fm=26&gp=0.jpg",
            "address": "0x884Ecbcd5960e92056578B80bb763c4f82cE67eD"
        },
        {
            "name": "PIGJLVE",
            "symbol": "PIGJLVE",
            "chainId": 128,
            "decimals": 18,
            "logoURI": "https://ss0.bdstatic.com/70cFvHSh_Q1YnxGkpoWK1HF6hhy/it/u=1021744422,3395550928&fm=26&gp=0.jpg",
            "address": "0x3d69D3FFD1269b9B1d0eE7b3BA28D25579A95e85"
        },
        {
            "name": "PIGPLHL",
            "symbol": "PIGPLHL",
            "chainId": 128,
            "decimals": 18,
            "logoURI": "https://ss0.bdstatic.com/70cFvHSh_Q1YnxGkpoWK1HF6hhy/it/u=1021744422,3395550928&fm=26&gp=0.jpg",
            "address": "0xeb120D7C631ce3332F20F54400Bb5B7353c32796"
        },
        {
            "name": "PIGZAKN",
            "symbol": "PIGZAKN",
            "chainId": 128,
            "decimals": 18,
            "logoURI": "https://ss0.bdstatic.com/70cFvHSh_Q1YnxGkpoWK1HF6hhy/it/u=1021744422,3395550928&fm=26&gp=0.jpg",
            "address": "0xA295068c1F2454FbA4F6F2df248bbE48F2436046"
        },
        {
            "name": "PIGKDKZ",
            "symbol": "PIGKDKZ",
            "chainId": 128,
            "decimals": 18,
            "logoURI": "https://ss0.bdstatic.com/70cFvHSh_Q1YnxGkpoWK1HF6hhy/it/u=1021744422,3395550928&fm=26&gp=0.jpg",
            "address": "0x0FA2EBce9608598497E1B04a243d5c0E0D4DaA05"
        },
        {
            "name": "PIGONTJ",
            "symbol": "PIGONTJ",
            "chainId": 128,
            "decimals": 18,
            "logoURI": "https://ss0.bdstatic.com/70cFvHSh_Q1YnxGkpoWK1HF6hhy/it/u=1021744422,3395550928&fm=26&gp=0.jpg",
            "address": "0xB003172563EB7545cee287a7e44B7D1a5c3D0570"
        },
        {
            "name": "PIGYKFS",
            "symbol": "PIGYKFS",
            "chainId": 128,
            "decimals": 18,
            "logoURI": "https://ss0.bdstatic.com/70cFvHSh_Q1YnxGkpoWK1HF6hhy/it/u=1021744422,3395550928&fm=26&gp=0.jpg",
            "address": "0xF3F190C9368C97c2C256d71C7D0F7B1f9d403734"
        },
        {
            "name": "PIGHLRG",
            "symbol": "PIGHLRG",
            "chainId": 128,
            "decimals": 18,
            "logoURI": "https://ss0.bdstatic.com/70cFvHSh_Q1YnxGkpoWK1HF6hhy/it/u=1021744422,3395550928&fm=26&gp=0.jpg",
            "address": "0x57fC9EC6C73C7bD7BE949702233814A852306ea0"
        },
        {
            "name": "PIGKXUF",
            "symbol": "PIGKXUF",
            "chainId": 128,
            "decimals": 18,
            "logoURI": "https://ss0.bdstatic.com/70cFvHSh_Q1YnxGkpoWK1HF6hhy/it/u=1021744422,3395550928&fm=26&gp=0.jpg",
            "address": "0xAB2a2838bba711e8cf0C5bF5e6aCfee6e41A06fb"
        },
        {
            "name": "PIGEVXJ",
            "symbol": "PIGEVXJ",
            "chainId": 128,
            "decimals": 18,
            "logoURI": "https://ss0.bdstatic.com/70cFvHSh_Q1YnxGkpoWK1HF6hhy/it/u=1021744422,3395550928&fm=26&gp=0.jpg",
            "address": "0x9303cedcfA7d97879d4Bf56DF27058891A0cdd5D"
        },
        {
            "name": "PIGHFYV",
            "symbol": "PIGHFYV",
            "chainId": 128,
            "decimals": 18,
            "logoURI": "https://ss0.bdstatic.com/70cFvHSh_Q1YnxGkpoWK1HF6hhy/it/u=1021744422,3395550928&fm=26&gp=0.jpg",
            "address": "0xA76438F04ec785cfD91CECb1E3bca61b94478Fe9"
        },
        {
            "name": "PIGWLWL",
            "symbol": "PIGWLWL",
            "chainId": 128,
            "decimals": 18,
            "logoURI": "https://ss0.bdstatic.com/70cFvHSh_Q1YnxGkpoWK1HF6hhy/it/u=1021744422,3395550928&fm=26&gp=0.jpg",
            "address": "0x59cde33050e89538dc7EE2adC1D66D83Bc2ff566"
        },
        {
            "name": "PIGJYNM",
            "symbol": "PIGJYNM",
            "chainId": 128,
            "decimals": 18,
            "logoURI": "https://ss0.bdstatic.com/70cFvHSh_Q1YnxGkpoWK1HF6hhy/it/u=1021744422,3395550928&fm=26&gp=0.jpg",
            "address": "0xFEa19EC3169Fa2D9B382e2BcFEb5e7aa9C325053"
        },
        {
            "name": "PIGPYAX",
            "symbol": "PIGPYAX",
            "chainId": 128,
            "decimals": 18,
            "logoURI": "https://ss0.bdstatic.com/70cFvHSh_Q1YnxGkpoWK1HF6hhy/it/u=1021744422,3395550928&fm=26&gp=0.jpg",
            "address": "0x75057Fb1a099d77bF356a8864C3419a1d88f6688"
        },
        {
            "name": "PIGIQKF",
            "symbol": "PIGIQKF",
            "chainId": 128,
            "decimals": 18,
            "logoURI": "https://ss0.bdstatic.com/70cFvHSh_Q1YnxGkpoWK1HF6hhy/it/u=1021744422,3395550928&fm=26&gp=0.jpg",
            "address": "0x38d3bC92B698a74d308b1BFC9A57DdAd27Fa89cB"
        },
        {
            "name": "PIGKRSG",
            "symbol": "PIGKRSG",
            "chainId": 128,
            "decimals": 18,
            "logoURI": "https://ss0.bdstatic.com/70cFvHSh_Q1YnxGkpoWK1HF6hhy/it/u=1021744422,3395550928&fm=26&gp=0.jpg",
            "address": "0x708a237B94E295503b7ffe99C68b2E93b357824F"
        },
        {
            "name": "PIGJPTI",
            "symbol": "PIGJPTI",
            "chainId": 128,
            "decimals": 18,
            "logoURI": "https://ss0.bdstatic.com/70cFvHSh_Q1YnxGkpoWK1HF6hhy/it/u=1021744422,3395550928&fm=26&gp=0.jpg",
            "address": "0x45Bd88348503a779eFcE71805fcb7B8322119A04"
        },
        {
            "name": "PIGVARW",
            "symbol": "PIGVARW",
            "chainId": 128,
            "decimals": 18,
            "logoURI": "https://ss0.bdstatic.com/70cFvHSh_Q1YnxGkpoWK1HF6hhy/it/u=1021744422,3395550928&fm=26&gp=0.jpg",
            "address": "0x3b43593a4Fc91955607cBEa8c92Bc1eF3e2c58A4"
        },
        {
            "name": "PIGFPAA",
            "symbol": "PIGFPAA",
            "chainId": 128,
            "decimals": 18,
            "logoURI": "https://ss0.bdstatic.com/70cFvHSh_Q1YnxGkpoWK1HF6hhy/it/u=1021744422,3395550928&fm=26&gp=0.jpg",
            "address": "0x328277a8093c6070A9e4E71A1BF1C1823C8b19ae"
        },
        {
            "name": "PIGDRWK",
            "symbol": "PIGDRWK",
            "chainId": 128,
            "decimals": 18,
            "logoURI": "https://ss0.bdstatic.com/70cFvHSh_Q1YnxGkpoWK1HF6hhy/it/u=1021744422,3395550928&fm=26&gp=0.jpg",
            "address": "0x3eF5135CE360FCd02DaA4919410342F98C8765A0"
        },
        {
            "name": "PIGCNRZ",
            "symbol": "PIGCNRZ",
            "chainId": 128,
            "decimals": 18,
            "logoURI": "https://ss0.bdstatic.com/70cFvHSh_Q1YnxGkpoWK1HF6hhy/it/u=1021744422,3395550928&fm=26&gp=0.jpg",
            "address": "0xadbe1184b8f98d0500ccb0B088bD6717F45bB7a4"
        },
        {
            "name": "PIGGQOE",
            "symbol": "PIGGQOE",
            "chainId": 128,
            "decimals": 18,
            "logoURI": "https://ss0.bdstatic.com/70cFvHSh_Q1YnxGkpoWK1HF6hhy/it/u=1021744422,3395550928&fm=26&gp=0.jpg",
            "address": "0x8043F23b5660c413167aA95Ff1BfDf59A1BE906A"
        },
        {
            "name": "PIGVBPF",
            "symbol": "PIGVBPF",
            "chainId": 128,
            "decimals": 18,
            "logoURI": "https://ss0.bdstatic.com/70cFvHSh_Q1YnxGkpoWK1HF6hhy/it/u=1021744422,3395550928&fm=26&gp=0.jpg",
            "address": "0x0a4626A95d88AD1D4C0eB5902209b3D10d15C709"
        },
        {
            "name": "PIGOJJW",
            "symbol": "PIGOJJW",
            "chainId": 128,
            "decimals": 18,
            "logoURI": "https://ss0.bdstatic.com/70cFvHSh_Q1YnxGkpoWK1HF6hhy/it/u=1021744422,3395550928&fm=26&gp=0.jpg",
            "address": "0xC61D8233810C8E0a0c71702C7B2874ACe196DcEB"
        },
        {
            "name": "PIGHPVQ",
            "symbol": "PIGHPVQ",
            "chainId": 128,
            "decimals": 18,
            "logoURI": "https://ss0.bdstatic.com/70cFvHSh_Q1YnxGkpoWK1HF6hhy/it/u=1021744422,3395550928&fm=26&gp=0.jpg",
            "address": "0xDd63FcD38e6Ced42ECbBD5E740F0E32A3fe71f3e"
        },
        {
            "name": "PIGOMXB",
            "symbol": "PIGOMXB",
            "chainId": 128,
            "decimals": 18,
            "logoURI": "https://ss0.bdstatic.com/70cFvHSh_Q1YnxGkpoWK1HF6hhy/it/u=1021744422,3395550928&fm=26&gp=0.jpg",
            "address": "0x60Ca0048Df3683476449F04eA5dE311cd24590cb"
        },
        {
            "name": "PIGKRUW",
            "symbol": "PIGKRUW",
            "chainId": 128,
            "decimals": 18,
            "logoURI": "https://ss0.bdstatic.com/70cFvHSh_Q1YnxGkpoWK1HF6hhy/it/u=1021744422,3395550928&fm=26&gp=0.jpg",
            "address": "0x94DEE8c989844d3116651180C417505751A439bc"
        },
        {
            "name": "PIGJPCL",
            "symbol": "PIGJPCL",
            "chainId": 128,
            "decimals": 18,
            "logoURI": "https://ss0.bdstatic.com/70cFvHSh_Q1YnxGkpoWK1HF6hhy/it/u=1021744422,3395550928&fm=26&gp=0.jpg",
            "address": "0x9cDE92CD3A4363Ed701372F3F3074f369c5E9f2C"
        },
        {
            "name": "PIGQRTK",
            "symbol": "PIGQRTK",
            "chainId": 128,
            "decimals": 18,
            "logoURI": "https://ss0.bdstatic.com/70cFvHSh_Q1YnxGkpoWK1HF6hhy/it/u=1021744422,3395550928&fm=26&gp=0.jpg",
            "address": "0xdf5BDCbb8676e4591281b9C779351bE274CA7f83"
        },
        {
            "name": "PIGFJHF",
            "symbol": "PIGFJHF",
            "chainId": 128,
            "decimals": 18,
            "logoURI": "https://ss0.bdstatic.com/70cFvHSh_Q1YnxGkpoWK1HF6hhy/it/u=1021744422,3395550928&fm=26&gp=0.jpg",
            "address": "0xC480826206121830c5d726830B15fef0b0eb30f6"
        },
        {
            "name": "PIGPHPK",
            "symbol": "PIGPHPK",
            "chainId": 128,
            "decimals": 18,
            "logoURI": "https://ss0.bdstatic.com/70cFvHSh_Q1YnxGkpoWK1HF6hhy/it/u=1021744422,3395550928&fm=26&gp=0.jpg",
            "address": "0x1c8aE80C43aDf134ba6bb07Cd09fa280Db25b6A8"
        },
        {
            "name": "PIGJSJZ",
            "symbol": "PIGJSJZ",
            "chainId": 128,
            "decimals": 18,
            "logoURI": "https://ss0.bdstatic.com/70cFvHSh_Q1YnxGkpoWK1HF6hhy/it/u=1021744422,3395550928&fm=26&gp=0.jpg",
            "address": "0x12dB0B170Ac58535bA5822D75Bb18Ea5948DB0b2"
        },
        {
            "name": "PIGUNZS",
            "symbol": "PIGUNZS",
            "chainId": 128,
            "decimals": 18,
            "logoURI": "https://ss0.bdstatic.com/70cFvHSh_Q1YnxGkpoWK1HF6hhy/it/u=1021744422,3395550928&fm=26&gp=0.jpg",
            "address": "0x1149bAB397B688C6191C44Dfb6CF0CDf841c4C95"
        },
        {
            "name": "PIGYLUI",
            "symbol": "PIGYLUI",
            "chainId": 128,
            "decimals": 18,
            "logoURI": "https://ss0.bdstatic.com/70cFvHSh_Q1YnxGkpoWK1HF6hhy/it/u=1021744422,3395550928&fm=26&gp=0.jpg",
            "address": "0xc8785D8d0617a1D5c595A78f89D6E42Aa98aBa82"
        },
        {
            "name": "PIGOOCK",
            "symbol": "PIGOOCK",
            "chainId": 128,
            "decimals": 18,
            "logoURI": "https://ss0.bdstatic.com/70cFvHSh_Q1YnxGkpoWK1HF6hhy/it/u=1021744422,3395550928&fm=26&gp=0.jpg",
            "address": "0x0D692a8a2A2BAE74E819b6b9Dd8C2adf04d54e73"
        },
        {
            "name": "PIGKWPP",
            "symbol": "PIGKWPP",
            "chainId": 128,
            "decimals": 18,
            "logoURI": "https://ss0.bdstatic.com/70cFvHSh_Q1YnxGkpoWK1HF6hhy/it/u=1021744422,3395550928&fm=26&gp=0.jpg",
            "address": "0x8C5BEe58892676c4373eD377E3839539f4FC099D"
        },
        {
            "name": "PIGJPGH",
            "symbol": "PIGJPGH",
            "chainId": 128,
            "decimals": 18,
            "logoURI": "https://ss0.bdstatic.com/70cFvHSh_Q1YnxGkpoWK1HF6hhy/it/u=1021744422,3395550928&fm=26&gp=0.jpg",
            "address": "0x9F37CEe7AF81A67B705ba57cc8861eF970664768"
        },
        {
            "name": "PIGFNSU",
            "symbol": "PIGFNSU",
            "chainId": 128,
            "decimals": 18,
            "logoURI": "https://ss0.bdstatic.com/70cFvHSh_Q1YnxGkpoWK1HF6hhy/it/u=1021744422,3395550928&fm=26&gp=0.jpg",
            "address": "0xcBFBf10E12Ba55b28d9b7C9aE651e20990Cfb598"
        },
        {
            "name": "PIGQTPR",
            "symbol": "PIGQTPR",
            "chainId": 128,
            "decimals": 18,
            "logoURI": "https://ss0.bdstatic.com/70cFvHSh_Q1YnxGkpoWK1HF6hhy/it/u=1021744422,3395550928&fm=26&gp=0.jpg",
            "address": "0xf9B74075dD42c60b66ddfC1c94240aF1A45DCfCa"
        },
        {
            "name": "PIGUBXJ",
            "symbol": "PIGUBXJ",
            "chainId": 128,
            "decimals": 18,
            "logoURI": "https://ss0.bdstatic.com/70cFvHSh_Q1YnxGkpoWK1HF6hhy/it/u=1021744422,3395550928&fm=26&gp=0.jpg",
            "address": "0xF6d0d8b02D188dBFFC7f9Ed0080c888eBd39dF9B"
        },
        {
            "name": "PIGKUKU",
            "symbol": "PIGKUKU",
            "chainId": 128,
            "decimals": 18,
            "logoURI": "https://ss0.bdstatic.com/70cFvHSh_Q1YnxGkpoWK1HF6hhy/it/u=1021744422,3395550928&fm=26&gp=0.jpg",
            "address": "0x7272b2b9dFdcDD6A3e82C97a26278B9a6FbA8B7c"
        },
        {
            "name": "PIGCEQP",
            "symbol": "PIGCEQP",
            "chainId": 128,
            "decimals": 18,
            "logoURI": "https://ss0.bdstatic.com/70cFvHSh_Q1YnxGkpoWK1HF6hhy/it/u=1021744422,3395550928&fm=26&gp=0.jpg",
            "address": "0x36BD831685D2660a4364e57Db010ACbC3DBe294F"
        },
        {
            "name": "PIGLYXP",
            "symbol": "PIGLYXP",
            "chainId": 128,
            "decimals": 18,
            "logoURI": "https://ss0.bdstatic.com/70cFvHSh_Q1YnxGkpoWK1HF6hhy/it/u=1021744422,3395550928&fm=26&gp=0.jpg",
            "address": "0x33a09f79A015FAA0BA615D7e803156Ec4Aa24955"
        },
        {
            "name": "PIGKEPV",
            "symbol": "PIGKEPV",
            "chainId": 128,
            "decimals": 18,
            "logoURI": "https://ss0.bdstatic.com/70cFvHSh_Q1YnxGkpoWK1HF6hhy/it/u=1021744422,3395550928&fm=26&gp=0.jpg",
            "address": "0x74c64bACDBc336caF346ab96BcCbD773E910780E"
        },
        {
            "name": "PIGPVZA",
            "symbol": "PIGPVZA",
            "chainId": 128,
            "decimals": 18,
            "logoURI": "https://ss0.bdstatic.com/70cFvHSh_Q1YnxGkpoWK1HF6hhy/it/u=1021744422,3395550928&fm=26&gp=0.jpg",
            "address": "0x61b6188e535fbb7E3E9356bfEE0490b32029B829"
        },
        {
            "name": "PIGYJEV",
            "symbol": "PIGYJEV",
            "chainId": 128,
            "decimals": 18,
            "logoURI": "https://ss0.bdstatic.com/70cFvHSh_Q1YnxGkpoWK1HF6hhy/it/u=1021744422,3395550928&fm=26&gp=0.jpg",
            "address": "0x275BD8181622E95140f83Fc4C944f99513e1c6fa"
        },
        {
            "name": "PIGKPDI",
            "symbol": "PIGKPDI",
            "chainId": 128,
            "decimals": 18,
            "logoURI": "https://ss0.bdstatic.com/70cFvHSh_Q1YnxGkpoWK1HF6hhy/it/u=1021744422,3395550928&fm=26&gp=0.jpg",
            "address": "0x3ae13dAb9E45D7CE99A09820814be3987476F571"
        },
        {
            "name": "PIGGUIE",
            "symbol": "PIGGUIE",
            "chainId": 128,
            "decimals": 18,
            "logoURI": "https://ss0.bdstatic.com/70cFvHSh_Q1YnxGkpoWK1HF6hhy/it/u=1021744422,3395550928&fm=26&gp=0.jpg",
            "address": "0xe8D954650e64bb5A5fA024Cb7883E7dF9BB0a151"
        },
        {
            "name": "PIGAIAT",
            "symbol": "PIGAIAT",
            "chainId": 128,
            "decimals": 18,
            "logoURI": "https://ss0.bdstatic.com/70cFvHSh_Q1YnxGkpoWK1HF6hhy/it/u=1021744422,3395550928&fm=26&gp=0.jpg",
            "address": "0xe9a09Cbe8A67fa41db9c347cED33E7B4634Ca699"
        },
        {
            "name": "PIGUEHN",
            "symbol": "PIGUEHN",
            "chainId": 128,
            "decimals": 18,
            "logoURI": "https://ss0.bdstatic.com/70cFvHSh_Q1YnxGkpoWK1HF6hhy/it/u=1021744422,3395550928&fm=26&gp=0.jpg",
            "address": "0xD17E209D1234890050b2A88C2acAD93556f1c11d"
        },
        {
            "name": "PIGBZOL",
            "symbol": "PIGBZOL",
            "chainId": 128,
            "decimals": 18,
            "logoURI": "https://ss0.bdstatic.com/70cFvHSh_Q1YnxGkpoWK1HF6hhy/it/u=1021744422,3395550928&fm=26&gp=0.jpg",
            "address": "0xBc9eBD378974F9F7f45b42d62981F344115F4B5b"
        },
        {
            "name": "PIGNLTZ",
            "symbol": "PIGNLTZ",
            "chainId": 128,
            "decimals": 18,
            "logoURI": "https://ss0.bdstatic.com/70cFvHSh_Q1YnxGkpoWK1HF6hhy/it/u=1021744422,3395550928&fm=26&gp=0.jpg",
            "address": "0xB9CAB2F66c9bfC0fFF3D3e98DcF2F75b01f3dCaE"
        },
        {
            "name": "PIGVNOM",
            "symbol": "PIGVNOM",
            "chainId": 128,
            "decimals": 18,
            "logoURI": "https://ss0.bdstatic.com/70cFvHSh_Q1YnxGkpoWK1HF6hhy/it/u=1021744422,3395550928&fm=26&gp=0.jpg",
            "address": "0xC0cAa7b07F6E1eDd73a5033FE6DB647f83D06f11"
        },
        {
            "name": "PIGCYNO",
            "symbol": "PIGCYNO",
            "chainId": 128,
            "decimals": 18,
            "logoURI": "https://ss0.bdstatic.com/70cFvHSh_Q1YnxGkpoWK1HF6hhy/it/u=1021744422,3395550928&fm=26&gp=0.jpg",
            "address": "0x81E0458884774C707D4178F07f31c444C33aBc5E"
        },
        {
            "name": "PIGIHNE",
            "symbol": "PIGIHNE",
            "chainId": 128,
            "decimals": 18,
            "logoURI": "https://ss0.bdstatic.com/70cFvHSh_Q1YnxGkpoWK1HF6hhy/it/u=1021744422,3395550928&fm=26&gp=0.jpg",
            "address": "0x0e0FB24f54d5881F286640f3A5B37291EB897a84"
        },
        {
            "name": "PIGAWHJ",
            "symbol": "PIGAWHJ",
            "chainId": 128,
            "decimals": 18,
            "logoURI": "https://ss0.bdstatic.com/70cFvHSh_Q1YnxGkpoWK1HF6hhy/it/u=1021744422,3395550928&fm=26&gp=0.jpg",
            "address": "0xEF527bcEfE6A312d5c423B27c81fb1fcEd645392"
        }
    ]
}